README.rst
setup.cfg
setup.py
qoo/__init__.py
qoo/errors.py
qoo/queues.py
qoo/utils.py
qoo.egg-info/PKG-INFO
qoo.egg-info/SOURCES.txt
qoo.egg-info/dependency_links.txt
qoo.egg-info/not-zip-safe
qoo.egg-info/requires.txt
qoo.egg-info/top_level.txt