Metadata-Version: 1.1
Name: qoo
Version: 0.0.4
Summary: A simple library for interacting with Amazon SQS.
Home-page: https://github.com/jpetrucciani/qoo.git
Author: Jacobi Petrucciani
Author-email: jacobi@mimirhq.com
License: MIT
Download-URL: https://github.com/jpetrucciani/qoo.git
Platform: UNKNOWN
Classifier: Programming Language :: Python :: 3
Classifier: Programming Language :: Python :: 3.5
Classifier: Programming Language :: Python :: 3.6
Classifier: Programming Language :: Python :: 3.7
Classifier: Programming Language :: Python :: Implementation :: CPython
Classifier: Programming Language :: Python :: Implementation :: PyPy
